arctic_ai/__init__.py
arctic_ai/cli.py
arctic_ai/cnn_prediction.py
arctic_ai/filters.py
arctic_ai/generate_graph.py
arctic_ai/gnn_prediction.py
arctic_ai/image_stitch.py
arctic_ai/ink_detection.py
arctic_ai/model_3d.py
arctic_ai/preprocessing.py
arctic_ai/scale_workflow.py
arctic_ai/tumor_map.py
arctic_ai/utils.py
arctic_ai/workflow.py
arctic_ai-0.1.dist-info/LICENSE
arctic_ai-0.1.dist-info/METADATA
arctic_ai-0.1.dist-info/WHEEL
arctic_ai-0.1.dist-info/entry_points.txt
arctic_ai-0.1.dist-info/top_level.txt
arctic_ai-0.1.dist-info/RECORD
