Metadata-Version: 2.1
Name: arctic-ai
Version: 0.1
Summary: Python package for Arctic Workflow. Mirrors jupyter developments.
Home-page: https://github.com/jlevy44/ArcticAI_Prototype
Author: Joshua Levy
Author-email: joshualevy44@berkeley.edu
License: MIT
License-File: LICENSE
Requires-Dist: alphashape (==1.3.1)
Requires-Dist: bracex (==2.3.post1)
Requires-Dist: charset-normalizer (==3.0.1)
Requires-Dist: click (==8.1.3)
Requires-Dist: click-log (==0.4.0)
Requires-Dist: cloudpickle (==2.2.1)
Requires-Dist: contourpy (==1.0.7)
Requires-Dist: cycler (==0.11.0)
Requires-Dist: dask (==2023.2.1)
Requires-Dist: distributed (==2023.2.1)
Requires-Dist: fire (==0.5.0)
Requires-Dist: fonttools (==4.38.0)
Requires-Dist: fsspec (==2023.1.0)
Requires-Dist: ghp-import (==2.1.0)
Requires-Dist: HeapDict (==1.0.1)
Requires-Dist: idna (==3.4)
Requires-Dist: imageio (==2.25.1)
Requires-Dist: importlib-metadata (==6.0.0)
Requires-Dist: importlib-resources (==5.12.0)
Requires-Dist: Jinja2 (==3.1.2)
Requires-Dist: joblib (==1.2.0)
Requires-Dist: kiwisolver (==1.4.4)
Requires-Dist: kornia (==0.6.10)
Requires-Dist: lazydocs (==0.4.8)
Requires-Dist: locket (==1.0.0)
Requires-Dist: Markdown (==3.3.7)
Requires-Dist: MarkupSafe (==2.1.2)
Requires-Dist: matplotlib (==3.7.0)
Requires-Dist: mergedeep (==1.3.4)
Requires-Dist: mkdocs (==1.4.2)
Requires-Dist: mkdocs-autorefs (==0.4.1)
Requires-Dist: mkdocs-awesome-pages-plugin (==2.8.0)
Requires-Dist: mkdocstrings (==0.20.0)
Requires-Dist: msgpack (==1.0.4)
Requires-Dist: natsort (==8.2.0)
Requires-Dist: networkx (==3.0)
Requires-Dist: numpy (==1.24.2)
Requires-Dist: opencv-python (==4.7.0.72)
Requires-Dist: packaging (==23.0)
Requires-Dist: pandas (==1.5.3)
Requires-Dist: partd (==1.3.0)
Requires-Dist: Pillow (==9.4.0)
Requires-Dist: psutil (==5.9.4)
Requires-Dist: pymdown-extensions (==9.9.2)
Requires-Dist: pyparsing (==3.0.9)
Requires-Dist: python-dateutil (==2.8.2)
Requires-Dist: pytz (==2022.7.1)
Requires-Dist: PyWavelets (==1.4.1)
Requires-Dist: PyYAML (==6.0)
Requires-Dist: pyyaml-env-tag (==0.1)
Requires-Dist: requests (==2.28.2)
Requires-Dist: Rtree (==1.0.1)
Requires-Dist: sauth (==1.1.0)
Requires-Dist: scikit-image (==0.18.3)
Requires-Dist: scikit-learn (==1.2.1)
Requires-Dist: scipy (==1.10.1)
Requires-Dist: seaborn (==0.12.2)
Requires-Dist: shapely (==2.0.1)
Requires-Dist: six (==1.16.0)
Requires-Dist: sortedcontainers (==2.4.0)
Requires-Dist: tblib (==1.7.0)
Requires-Dist: termcolor (==2.2.0)
Requires-Dist: threadpoolctl (==3.1.0)
Requires-Dist: tifffile (==2021.11.2)
Requires-Dist: pyamg (==5.0.0)
Requires-Dist: opencv-contrib-python (==4.5.5.62)
Requires-Dist: toolz (==0.12.0)
Requires-Dist: torch (==1.13.1)
Requires-Dist: torchaudio (==0.13.1)
Requires-Dist: torchvision (==0.14.1)
Requires-Dist: tornado (==6.2)
Requires-Dist: tqdm (==4.64.1)
Requires-Dist: trimesh (==3.20.1)
Requires-Dist: typer (==0.7.0)
Requires-Dist: typing-extensions (==4.5.0)
Requires-Dist: urllib3 (==1.26.14)
Requires-Dist: watchdog (==2.3.0)
Requires-Dist: wcmatch (==8.4.1)
Requires-Dist: zict (==2.2.0)
Requires-Dist: zipp (==3.15.0)
Requires-Dist: toil (==5.9.2)
